sparkless/__init__.py
sparkless/_version.py
sparkless/config.py
sparkless/delta.py
sparkless/error_simulation.py
sparkless/errors.py
sparkless/performance_simulation.py
sparkless/py.typed
sparkless/spark_types.py
sparkless/window.py
sparkless/backend/__init__.py
sparkless/backend/factory.py
sparkless/backend/protocols.py
sparkless/backend/polars/__init__.py
sparkless/backend/polars/export.py
sparkless/backend/polars/expression_translator.py
sparkless/backend/polars/materializer.py
sparkless/backend/polars/operation_executor.py
sparkless/backend/polars/parquet_storage.py
sparkless/backend/polars/schema_registry.py
sparkless/backend/polars/schema_utils.py
sparkless/backend/polars/storage.py
sparkless/backend/polars/type_mapper.py
sparkless/backend/polars/window_handler.py
sparkless/backend/polars/executors/__init__.py
sparkless/backend/polars/translators/__init__.py
sparkless/backend/polars/translators/arithmetic_translator.py
sparkless/backend/polars/translators/string_translator.py
sparkless/backend/polars/translators/type_translator.py
sparkless/compat/__init__.py
sparkless/compat/datetime.py
sparkless/core/__init__.py
sparkless/core/column_resolver.py
sparkless/core/condition_evaluator.py
sparkless/core/data_validation.py
sparkless/core/ddl_adapter.py
sparkless/core/protocols.py
sparkless/core/safe_evaluator.py
sparkless/core/schema_inference.py
sparkless/core/type_utils.py
sparkless/core/exceptions/__init__.py
sparkless/core/exceptions/analysis.py
sparkless/core/exceptions/base.py
sparkless/core/exceptions/execution.py
sparkless/core/exceptions/operation.py
sparkless/core/exceptions/py4j_compat.py
sparkless/core/exceptions/runtime.py
sparkless/core/exceptions/validation.py
sparkless/core/interfaces/__init__.py
sparkless/core/interfaces/dataframe.py
sparkless/core/interfaces/functions.py
sparkless/core/interfaces/session.py
sparkless/core/interfaces/storage.py
sparkless/core/types/__init__.py
sparkless/core/types/data_types.py
sparkless/core/types/metadata.py
sparkless-3.27.1.dist-info/METADATA
sparkless-3.27.1.dist-info/WHEEL
sparkless-3.27.1.dist-info/top_level.txt
sparkless-3.27.1.dist-info/RECORD
